forbiddenfp/__init__.py
forbiddenfp-0.9.9.3.dist-info/LICENSE
forbiddenfp-0.9.9.3.dist-info/METADATA
forbiddenfp-0.9.9.3.dist-info/WHEEL
forbiddenfp-0.9.9.3.dist-info/top_level.txt
forbiddenfp-0.9.9.3.dist-info/RECORD
