Metadata-Version: 2.1
Name: forbiddenfp
Version: 0.9.9.3
Summary: Forbidden Functional Programming in Python.
Home-page: https://github.com/yx-z/forbiddenfp
Author: David
Author-email: yx-z <yx-z@outlook.com>
Project-URL: Homepage, https://github.com/yx-z/forbiddenfp
Project-URL: Issues, https://github.com/yx-z/forbiddenfp/issues
Classifier: Programming Language :: Python :: 3
Classifier: License :: OSI Approved :: MIT License
Classifier: Operating System :: OS Independent
Requires-Python: >=3.7
License-File: LICENSE
Requires-Dist: forbiddenfruit
Requires-Dist: typing-extensions
